mwaatk/__init__.py
mwaatk/absorbancecalculator.py
mwaatk/alphaminimizer.py
mwaatk/angstrom.py
mwaatk/compoundpreprocessor.py
mwaatk/dataset.py
mwaatk/datasetabsorbancecalculator.py
mwaatk/datasetfromfile.py
mwaatk/filtersample.py
mwaatk/preprocessor.py
mwaatk/toolkit.py
mwaatk-1.0.2.dist-info/entry_points.txt
mwaatk-1.0.2.dist-info/WHEEL
mwaatk-1.0.2.dist-info/METADATA
mwaatk-1.0.2.dist-info/RECORD
